Topsis_Arsh/__init__.py
Topsis_Arsh/topsis.py
Topsis_Arsh-0.0.2.dist-info/LICENSE.txt
Topsis_Arsh-0.0.2.dist-info/METADATA
Topsis_Arsh-0.0.2.dist-info/WHEEL
Topsis_Arsh-0.0.2.dist-info/top_level.txt
Topsis_Arsh-0.0.2.dist-info/RECORD
